cjkformat/__init__.py
cjkformat/cjkformat.py
cjkformat-0.1.1.dist-info/LICENSE
cjkformat-0.1.1.dist-info/METADATA
cjkformat-0.1.1.dist-info/WHEEL
cjkformat-0.1.1.dist-info/top_level.txt
cjkformat-0.1.1.dist-info/RECORD
