Metadata-Version: 2.1
Name: cjkformat
Version: 0.1.1
Summary: This Python 3 module provides utility functions for formatting fixed-width CJK strings.
Home-page: https://github.com/HuidaeCho/cjkformat
Author: Huidae Cho
Author-email: grass4u@gmail.com
License: UNKNOWN
Platform: UNKNOWN
Classifier: Programming Language :: Python :: 3
Classifier: License :: OSI Approved :: GNU General Public License v3 or later (GPLv3+)
Classifier: Operating System :: OS Independent
Requires-Python: >=3
